geojson_msgspec/__init__.py
geojson_msgspec/py.typed
geojson_msgspec-1.0.0.dist-info/METADATA
geojson_msgspec-1.0.0.dist-info/WHEEL
geojson_msgspec-1.0.0.dist-info/licenses/LICENSE
geojson_msgspec-1.0.0.dist-info/RECORD
