Metadata-Version: 2.4
Name: geojson-msgspec
Version: 1.0.0
Summary: msgspec GeoJSON model
License-File: LICENSE
Requires-Python: >=3.9
Requires-Dist: msgspec<0.20,>=0.19
